datamapplot/__init__.py
datamapplot/alpha_shapes.py
datamapplot/config.py
datamapplot/create_plots.py
datamapplot/deckgl_template.html
datamapplot/edge_bundling.py
datamapplot/fonts.py
datamapplot/histograms.py
datamapplot/interactive_rendering.py
datamapplot/medoids.py
datamapplot/offline_mode_caching.py
datamapplot/overlap_computations.py
datamapplot/palette_handling.py
datamapplot/plot_rendering.py
datamapplot/selection_handlers.py
datamapplot/text_placement.py
datamapplot/static/css/colormap_selector_style.css
datamapplot/static/css/containers_and_stacks.css
datamapplot/static/css/d3_histogram_style.css
datamapplot/static/css/progress_bar_style.css
datamapplot/static/css/topic_tree_style.css
datamapplot/static/js/colormap_selector.js
datamapplot/static/js/d3_histogram.js
datamapplot/static/js/data_selection_manager.js
datamapplot/static/js/datamap.js
datamapplot/static/js/dynamic_tooltip.js
datamapplot/static/js/lasso_selection.js
datamapplot/static/js/quad_tree.js
datamapplot/static/js/topic_tree.js
datamapplot-0.6.4.dist-info/LICENSE
datamapplot-0.6.4.dist-info/METADATA
datamapplot-0.6.4.dist-info/WHEEL
datamapplot-0.6.4.dist-info/entry_points.txt
datamapplot-0.6.4.dist-info/top_level.txt
datamapplot-0.6.4.dist-info/RECORD
