Metadata-Version: 2.1
Name: datamapplot
Version: 0.6.4
Summary: A library for presentation and publication ready plots of data maps
Home-page: https://github.com/TutteInstitute/datamapplot
Author: Leland McInnes
Author-email: leland.mcinnes@gmail.com
Maintainer: Leland McInnes
Maintainer-email: leland.mcinnes@gmail.com
License: MIT License
Keywords: data map,visualization,topic modelling,cluster,clustering
Classifier: License :: OSI Approved :: MIT License
Classifier: Programming Language :: Python :: 3.9
Classifier: Programming Language :: Python :: 3.10
Classifier: Programming Language :: Python :: 3.11
Classifier: Programming Language :: Python :: 3.12
Classifier: Development Status :: 4 - Beta
Classifier: Operating System :: OS Independent
Requires-Python: >=3.9
License-File: LICENSE
Requires-Dist: colorcet
Requires-Dist: colorspacious>=1.1
Requires-Dist: dask[complete]<2025.0.1,>=2024.4.1
Requires-Dist: datashader>=0.16
Requires-Dist: importlib-resources
Requires-Dist: jinja2
Requires-Dist: matplotlib>=3.8
Requires-Dist: numba>=0.56
Requires-Dist: numpy>=1.21
Requires-Dist: pandas>=1.0
Requires-Dist: pyarrow
Requires-Dist: pylabeladjust
Requires-Dist: requests
Requires-Dist: rcssmin>=1.1.2
Requires-Dist: rjsmin>=1.2.2
Requires-Dist: scikit-image>=0.22
Requires-Dist: scikit-learn>=1.1
Requires-Dist: platformdirs
Requires-Dist: typing-extensions
